<?xml version='1.0' encoding='utf-8'?>
<nrml xmlns:gml="http://www.opengis.net/gml" xmlns="http://openquake.org/xmlns/nrml/0.4">
  <sourceModel name="Banda_Detachment">
  <complexFaultSource id="1234" name="Banda_Detachment_AustPTHA" tectonicRegion="SubductionInterface">

      <complexFaultGeometry>
        <faultTopEdge>
          <gml:LineString>
            <gml:posList>
               129.5993838130 -3.3759715415 0.001
               129.9231812067 -3.7052695071 0.001
               130.2862861994 -4.2520084367 0.001
               130.4996685835 -4.5803659436 0.001
               130.6217932915 -5.0508467916 0.001
               130.6861667300 -5.4954454400 0.001
               130.7037827100 -5.8228090200 0.001
               130.5628548900 -6.0738367100 0.001
               130.0774259676 -6.7156382955 0.001
               128.8680857787 -7.4437669517 0.001
               128.5017691820 -7.5356830754 0.001
            </gml:posList>
          </gml:LineString>
        </faultTopEdge>

        <intermediateEdge>
          <gml:LineString>
            <gml:posList>
               129.5555996439 -3.4360613268 5.0
               129.9025309398 -3.8407120394 5.0
               130.1269491487 -4.2454139945 5.0
               130.2526623796 -4.6606670821 5.0
               130.3226733926 -4.9187588655 5.0
               130.3942121425 -5.1700395498 5.0
               130.3917865013 -5.4294830031 5.0
               130.3806543723 -5.7519741866 5.0
               130.2938343652 -5.9400359956 5.0
               130.1273680993 -6.2453280228 5.0
               129.8974054938 -6.4722838768 5.0
               129.7307671198 -6.6516829690 5.0
               129.5185896905 -6.8598211395 5.0
               128.8538563381 -7.3246524399 5.0
               128.4803673950 -7.4475493235 5.0
            </gml:posList>
          </gml:LineString>
        </intermediateEdge>

        <intermediateEdge>
          <gml:LineString>
            <gml:posList>
               129.4804829368 -3.4789851594 10.0
               129.6319058787 -3.6712765294 10.0
               129.8506456144 -3.9568898665 10.0
               129.9805667009 -4.3065278766 10.0
               130.0347203302 -4.6056179208 10.0
               130.0243169687 -5.0662047679 10.0
               130.0508240929 -5.2245543529 10.0
               130.0171248390 -5.4068697444 10.0
               130.0020392229 -5.5555623507 10.0
               129.8604160089 -6.0331149959 10.0
               129.5337873778 -6.6297383316 10.0
               129.4026402823 -6.7659664002 10.0
               129.1586372045 -6.9744501774 10.0
               128.8436676741 -7.2129966706 10.0
               128.4536688947 -7.3653016846 10.0

            </gml:posList>
          </gml:LineString>
        </intermediateEdge>

        <intermediateEdge>
          <gml:LineString>
            <gml:posList>
               129.4080317858 -3.5305642206 15.0
               129.5900611819 -3.7780988671 15.0
               129.7174603984 -4.0114960125 15.0
               129.7531943362 -4.3130575736 15.0
               129.7988138007 -4.6110103499 15.0
               129.7652855974 -4.8074940824 15.0
               129.6861993150 -4.9960940739 15.0
               129.5941906700 -5.4327597824 15.0
               129.4728843632 -5.7454138736 15.0
               129.3913242852 -6.0758770333 15.0
               129.2992409216 -6.5576808841 15.0
               129.1756878363 -6.7900293681 15.0
               128.7966294076 -7.1173114248 15.0
               128.4452470637 -7.2568442541 15.0
            </gml:posList>
          </gml:LineString>
        </intermediateEdge>

        <faultBottomEdge>
          <gml:LineString>
            <gml:posList>
               129.3461139450 -3.6053412506 20.0
               129.4729282082 -3.8121066366 20.0
               129.5564954276 -4.0728042682 20.0
               129.5336489820 -4.3299539139 20.0
               129.4778162738 -4.5061281540 20.0
               129.2600203620 -4.9574866906 20.0
               129.0765656898 -5.5856054414 20.0
               129.0346478845 -6.1974489056 20.0
               128.9272935907 -6.7019604321 20.0
               128.6993054422 -6.9632145509 20.0
               128.4060372982 -7.1753968923 20.0
            </gml:posList>
          </gml:LineString>
        </faultBottomEdge>
      </complexFaultGeometry>

      <magScaleRel>StrasserInterface</magScaleRel>

      <ruptAspectRatio>1.5</ruptAspectRatio>

      <truncGutenbergRichterMFD aValue="20" bValue="1.0" minMag="6.5" maxMag="9.5" />

      <rake>-90</rake>
    </complexFaultSource>
  </sourceModel>
</nrml>
